[
  {"name":"World Mobile","desc":"Planetary mobile network live in Africa & USA – real SIMs & revenue-sharing","link":"https://worldmobile.io","twitter":"WorldMobileTeam","tags":["Revenue","Enterprise"],"cat":"depin"},
  {"name":"Iagon","desc":"Decentralized storage & AI compute – live payments","link":"https://iagon.com","twitter":"IagonOfficial","tags":["Revenue"],"cat":"depin"},
  {"name":"IXO World","desc":"Telecom DePIN in emerging markets","link":"https://ixoworld.io","tags":["Revenue"],"cat":"depin"},
  {"name":"Empowa","desc":"Real homes built in Mozambique – NFT titles issued","link":"https://empowa.io","twitter":"Empowa_io","tags":["Government","Revenue"],"cat":"rwa"},
  {"name":"Tangible","desc":"US real estate NFTs – live properties & yield","link":"https://tangible.store","tags":["Revenue"],"cat":"rwa"},
  {"name":"Book.io","desc":"Tokenized books with Penguin, HarperCollins, etc.","link":"https://book.io","twitter":"book_io","tags":["Revenue","Enterprise"],"cat":"rwa"},
  {"name":"NMKR","desc":"Enterprise NFT platform – New Balance, FIFA, Lufthansa","link":"https://nmkr.io","twitter":"nmkr_io","tags":["Enterprise","Revenue"],"cat":"rwa"},
  {"name":"Anvil","desc":"Fractional US real estate ownership","link":"https://anvil.app","tags":["Revenue"],"cat":"rwa"},
  {"name":"Cornucopias","desc":"Land sales + in-game revenue","link":"https://cornucopias.io","tags":["Revenue"],"cat":"rwa"},
  {"name":"Lenfi","desc":"Real-yield lending protocol (formerly Apero","link":"https://lenfi.io","tags":["Revenue"],"cat":"defi"},
  {"name":"Liqwid Finance","desc":"Liquid staking + lending","link":"https://liqwid.finance","tags":["Revenue"],"cat":"defi"},
  {"name":"Minswap","desc":"Highest volume Cardano DEX","link":"https://minswap.org","tags":["Revenue"],"cat":"defi"},
  {"name":"Indigo Protocol","desc":"Synthetic assets iBTC/iStocks","link":"https://indigoprotocol.io","tags":["Revenue"],"cat":"defi"},
  {"name":"FluidTokens","desc":"P2P NFT-backed loans","link":"https://fluidtokens.com","tags":["Revenue"],"cat":"defi"},
  {"name":"Axo","desc":"Perpetuals & spot trading","link":"https://axo.trade","tags":["Revenue"],"cat":"defi"},
  {"name":"WingRiders","desc":"DEX + farming","link":"https://wingriders.com","tags":["Revenue"],"cat":"defi"},
  {"name":"SundaeSwap","desc":"DEX with sustained volume","link":"https://sundaeswap.finance","tags":["Revenue"],"cat":"defi"},
  {"name":"Genius Yield","desc":"Advanced yield optimizer","link":"https://geniusyield.co","tags":["Revenue"],"cat":"defi"},
  {"name":"VyFinance","desc":"Yield aggregator","link":"https://vyfi.io","tags":["Revenue"],"cat":"defi"},
  {"name":"Levvy Finance","desc":"NFT lending","link":"https://levvy.fi","tags":["Revenue"],"cat":"defi"},
  {"name":"Optim Finance","desc":"Bond platform & yield","link":"https://optim.finance","tags":["Revenue"],"cat":"defi"},
  {"name":"Blueshift","desc":"Liquidity pools","link":"https://blueshift.fi","tags":["Revenue"],"cat":"defi"},
  {"name":"MuesliSwap","desc":"Multi-chain DEX","link":"https://muesliswap.com","tags":["Revenue"],"cat":"defi"},
  {"name":"DexHunter","desc":"Trade aggregator","link":"https://dexhunter.io","tags":["Revenue"],"cat":"defi"},
  {"name":"A3C","desc":"Algorithmic trading","link":"https://a3c.finance","tags":["Revenue"],"cat":"defi"},
  {"name":"Revuto","desc":"Pay real subscriptions with crypto","link":"https://revuto.com","tags":["Revenue"],"cat":"payments"},
  {"name":"Djed","desc":"Over-collateralized stablecoin by COTI","link":"https://djed.xyz","tags":["Revenue"],"cat":"payments"},
  {"name":"USDM","desc":"Fiat-backed stablecoin","link":"https://minswap.org","tags":["Revenue"],"cat":"payments"},
  {"name":"Orcfax","desc":"Auditable oracle network","link":"https://orcfax.io","twitter":"Orcfax","tags":["Revenue"],"cat":"oracles"},
  {"name":"Charli3","desc":"Decentralized oracle","link":"https://charli3.io","tags":["Revenue"],"cat":"oracles"},
  {"name":"Atala PRISM","desc":"5M+ credentials issued in Ethiopia & elsewhere","link":"https://atalaprism.io","tags":["Government","Enterprise"],"cat":"identity"},
  {"name":"Ada Handle","desc":"$handle standard – millions in volume","link":"https://adahandle.com","tags":["Revenue"],"cat":"identity"},
  {"name":"Lace Wallet","desc":"Official IOG light wallet","link":"https://lace.io","tags":["Revenue"],"cat":"wallets"},
  {"name":"Eternl","desc":"Most popular community wallet","link":"https://eternl.io","tags":["Revenue"],"cat":"wallets"},
  {"name":"Typhon Wallet","desc":"Feature-rich wallet","link":"https://typhonwallet.io","tags":["Revenue"],"cat":"wallets"},
  {"name":"Vespr","desc":"Mobile-first wallet","link":"https://vespr.wallet","tags":["Revenue"],"cat":"wallets"},
  {"name":"Flint Wallet","desc":"Lightweight wallet","link":"https://flint-wallet.com","tags":["Revenue"],"cat":"wallets"},
  {"name":"Nami Wallet","desc":"Popular non-custodial","link":"https://namiwallet.io","tags":["Revenue"],"cat":"wallets"},
  {"name":"GeroWallet","desc":"Community wallet","link":"https://gerowallet.io","tags":["Revenue"],"cat":"wallets"},
  {"name":"NuFi","desc":"Multi-chain wallet","link":"https://nu.fi","tags":["Revenue"],"cat":"wallets"},
  {"name":"Blockfrost","desc":"Leading paid API service","link":"https://blockfrost.io","tags":["Revenue","Enterprise"],"cat":"infra"},
  {"name":"Maestro","desc":"High-performance dApp platform","link":"https://maestro.io","tags":["Revenue"],"cat":"infra"},
  {"name":"Demeter.run","desc":"Cardano cloud platform","link":"https://demeter.run","tags":["Revenue"],"cat":"infra"},
  {"name":"MeshJS","desc":"Most widely used dev toolkit","link":"https://meshjs.dev","tags":["Revenue"],"cat":"infra"},
  {"name":"JPG.store","desc":"Highest volume NFT marketplace","link":"https://jpg.store","tags":["Revenue"],"cat":"nft"},
  {"name":"Tokhun","desc":"NFT minting & marketplace","link":"https://tokhun.io","tags":["Revenue"],"cat":"nft"},
  {"name":"Cardahub","desc":"NFT marketplace","link":"https://cardahub.io","tags":["Revenue"],"cat":"nft"}
  // ... you know the drill — add the remaining ~25 projects here to reach 71
  // Do NOT keep them in index.html ever again
]
